ut_path/__init__.py
ut_path/__version__.py
ut_path/aodopath.py
ut_path/aopath.py
ut_path/path.py
ut_path/pathk.py
ut_path/py.typed
ut_path-2.0.0.20251020.dist-info/licenses/LICENSE.txt
ut_path-2.0.0.20251020.dist-info/METADATA
ut_path-2.0.0.20251020.dist-info/WHEEL
ut_path-2.0.0.20251020.dist-info/top_level.txt
ut_path-2.0.0.20251020.dist-info/RECORD
