Metadata-Version: 2.4
Name: ut_path
Version: 2.0.0.20251020
Summary: Utilities for Path Management
Author-email: Bernd Stroehle <bernd.stroehle@gmail.com>
Maintainer-email: Bernd Stroehle <bernd.stroehle@gmail.com>
License-Expression: GPL-3.0-only WITH Classpath-exception-2.0 OR BSD-3-Clause
Project-URL: Source Code, https://github.com/bs29/ut_path/tree/master
Project-URL: Homepage, https://kosakya.de/
Project-URL: Documentation, https://ka-apc.readthedocs.io/en/latest
Classifier: Development Status :: 5 - Production/Stable
Classifier: Intended Audience :: Developers
Classifier: Operating System :: OS Independent
Classifier: Programming Language :: Python :: 3.12
Classifier: Natural Language :: English
Classifier: Topic :: Software Development :: Libraries :: Python Modules
Requires-Python: >=3.10
License-File: LICENSE.txt
Requires-Dist: pandas>=2.3.3
Requires-Dist: ut_aod>=1.4.5.20251009
Requires-Dist: ut_dic>=1.5.5.20251011
Requires-Dist: ut_log>=1.3.4.20251009
Requires-Dist: ut_obj>=1.2.3.20251009
Requires-Dist: ut_pac>=1.2.6.20251009
Dynamic: license-file
